diffsynth/__init__.py
diffsynth/configs/__init__.py
diffsynth/configs/model_configs.py
diffsynth/configs/vram_management_module_maps.py
diffsynth/core/__init__.py
diffsynth/core/attention/__init__.py
diffsynth/core/attention/attention.py
diffsynth/core/data/__init__.py
diffsynth/core/data/operators.py
diffsynth/core/data/unified_dataset.py
diffsynth/core/device/__init__.py
diffsynth/core/device/npu_compatible_device.py
diffsynth/core/gradient/__init__.py
diffsynth/core/gradient/gradient_checkpoint.py
diffsynth/core/loader/__init__.py
diffsynth/core/loader/config.py
diffsynth/core/loader/file.py
diffsynth/core/loader/model.py
diffsynth/core/vram/__init__.py
diffsynth/core/vram/disk_map.py
diffsynth/core/vram/initialization.py
diffsynth/core/vram/layers.py
diffsynth/diffusion/__init__.py
diffsynth/diffusion/base_pipeline.py
diffsynth/diffusion/flow_match.py
diffsynth/diffusion/logger.py
diffsynth/diffusion/loss.py
diffsynth/diffusion/parsers.py
diffsynth/diffusion/runner.py
diffsynth/diffusion/training_module.py
diffsynth/models/dinov3_image_encoder.py
diffsynth/models/flux2_dit.py
diffsynth/models/flux2_text_encoder.py
diffsynth/models/flux2_vae.py
diffsynth/models/flux_controlnet.py
diffsynth/models/flux_dit.py
diffsynth/models/flux_infiniteyou.py
diffsynth/models/flux_ipadapter.py
diffsynth/models/flux_lora_encoder.py
diffsynth/models/flux_lora_patcher.py
diffsynth/models/flux_text_encoder_clip.py
diffsynth/models/flux_text_encoder_t5.py
diffsynth/models/flux_vae.py
diffsynth/models/flux_value_control.py
diffsynth/models/general_modules.py
diffsynth/models/longcat_video_dit.py
diffsynth/models/model_loader.py
diffsynth/models/nexus_gen.py
diffsynth/models/nexus_gen_ar_model.py
diffsynth/models/nexus_gen_projector.py
diffsynth/models/qwen_image_controlnet.py
diffsynth/models/qwen_image_dit.py
diffsynth/models/qwen_image_image2lora.py
diffsynth/models/qwen_image_text_encoder.py
diffsynth/models/qwen_image_vae.py
diffsynth/models/sd_text_encoder.py
diffsynth-2.0.4.dist-info/licenses/LICENSE
diffsynth-2.0.4.dist-info/METADATA
diffsynth-2.0.4.dist-info/WHEEL
diffsynth-2.0.4.dist-info/top_level.txt
diffsynth-2.0.4.dist-info/RECORD
