Metadata-Version: 2.4
Name: diffsynth
Version: 2.0.4
Summary: Enjoy the magic of Diffusion models!
Author: ModelScope Team
License: Apache-2.0
Classifier: Programming Language :: Python :: 3
Classifier: License :: OSI Approved :: Apache Software License
Classifier: Operating System :: OS Independent
Requires-Python: >=3.10.1
License-File: LICENSE
Requires-Dist: torch>=2.0.0
Requires-Dist: torchvision
Requires-Dist: transformers
Requires-Dist: imageio
Requires-Dist: imageio[ffmpeg]
Requires-Dist: safetensors
Requires-Dist: einops
Requires-Dist: sentencepiece
Requires-Dist: protobuf
Requires-Dist: modelscope
Requires-Dist: ftfy
Requires-Dist: pandas
Requires-Dist: accelerate
Requires-Dist: peft
Requires-Dist: datasets
Provides-Extra: npu-aarch64
Requires-Dist: torch==2.7.1; extra == "npu-aarch64"
Requires-Dist: torch-npu==2.7.1; extra == "npu-aarch64"
Requires-Dist: torchvision==0.22.1; extra == "npu-aarch64"
Provides-Extra: npu
Requires-Dist: torch==2.7.1+cpu; extra == "npu"
Requires-Dist: torch-npu==2.7.1; extra == "npu"
Requires-Dist: torchvision==0.22.1+cpu; extra == "npu"
Dynamic: license-file
